flask_faas/aws.py
flask_faas/azure.py
flask_faas/gcp.py
flask_faas-0.0.1.dist-info/LICENSE.txt
flask_faas-0.0.1.dist-info/METADATA
flask_faas-0.0.1.dist-info/WHEEL
flask_faas-0.0.1.dist-info/top_level.txt
flask_faas-0.0.1.dist-info/RECORD
