Metadata-Version: 2.1
Name: flask-faas
Version: 0.0.1
Summary: flask serverless decorator
Home-page: https://github.com/Glitchfix/flask-faas
Author: Shivanjan Chakravorty
Author-email: schakravorty846@gmail.com
License: MIT
Download-URL: https://github.com/Glitchfix/flask-faas/archive/refs/tags/0.1.tar.gz
Project-URL: Bug Tracker, https://github.com/Glitchfix/flask-faas/issues
Keywords: flask,serverless,faas,flask-serverless,lambda,cloud function,flask serverless
Platform: UNKNOWN
Classifier: Development Status :: 5 - Production/Stable
Classifier: Intended Audience :: Developers
Classifier: Topic :: Internet :: WWW/HTTP :: WSGI
Classifier: License :: OSI Approved :: MIT License
Classifier: Programming Language :: Python :: 3
Classifier: Programming Language :: Python :: 3.6
Classifier: Programming Language :: Python :: 3.7
Classifier: Programming Language :: Python :: 3.8
Classifier: Programming Language :: Python :: 3.9
Classifier: Programming Language :: Python :: 3.10
License-File: LICENSE.txt
Requires-Dist: flask
Requires-Dist: pytest
